LICENSE
MANIFEST.in
README.md
setup.py
cmsplugin_photologue/__init__.py
cmsplugin_photologue/cms_plugins.py
cmsplugin_photologue/models.py
cmsplugin_photologue/settings.py
cmsplugin_photologue.egg-info/PKG-INFO
cmsplugin_photologue.egg-info/SOURCES.txt
cmsplugin_photologue.egg-info/dependency_links.txt
cmsplugin_photologue.egg-info/requires.txt
cmsplugin_photologue.egg-info/top_level.txt
cmsplugin_photologue/locale/cs/LC_MESSAGES/django.mo
cmsplugin_photologue/locale/cs/LC_MESSAGES/django.po
cmsplugin_photologue/migrations/0001_initial.py
cmsplugin_photologue/migrations/__init__.py
cmsplugin_photologue/templates/cmsplugin_photologue/gallery-default.html
cmsplugin_photologue/templates/cmsplugin_photologue/photo-center.html
cmsplugin_photologue/templates/cmsplugin_photologue/photo-default.html
cmsplugin_photologue/templates/cmsplugin_photologue/photo-left.html
cmsplugin_photologue/templates/cmsplugin_photologue/photo-right.html